raiden_py/__init__.py
raiden_py/raiden.py
raiden_py-0.1.2.dist-info/METADATA
raiden_py-0.1.2.dist-info/WHEEL
raiden_py-0.1.2.dist-info/top_level.txt
raiden_py-0.1.2.dist-info/RECORD
