Metadata-Version: 2.1
Name: raiden-py
Version: 0.1.2
Summary: Raiden Python Client Library
Home-page: https://github.com/viraja1/raiden_py/
Author: viraj
Author-email: 
License: MIT
Keywords: raiden
Platform: UNKNOWN
Classifier: Development Status :: 3 - Alpha
Classifier: Intended Audience :: Developers
Classifier: License :: OSI Approved :: MIT License
Classifier: Natural Language :: English
Classifier: Programming Language :: Python :: 3
Classifier: Programming Language :: Python :: 3.7
Requires-Python: >=3.7
Requires-Dist: requests (>=2.20.0)
